{
	"file_path": "C:\\Users\\Adam\\AppData\\Local\\Packages\\Microsoft.MinecraftUWP_8wekyb3d8bbwe\\LocalState\\games\\com.mojang\\development_behavior_packs\\POW BP\\entities\\iron_golem.json",
	"file_type": "entity",
	"format_version": 1,
	"file_uuid": "a078ba8d_d538_4e20_b97d_297671a2b96a",
	"file_version": 0,
	"cache_content": {
		"open": true,
		"comment": "",
		"data": "",
		"key": "global",
		"type": "object",
		"meta": {},
		"children": [
			{
				"open": false,
				"comment": "",
				"data": "1.13.0",
				"key": "format_version",
				"type": "string",
				"meta": {},
				"children": []
			},
			{
				"open": true,
				"comment": "",
				"data": "",
				"key": "minecraft:entity",
				"type": "object",
				"meta": {
					"expand_path_exceptions": [
						"do_not_upgrade"
					]
				},
				"children": [
					{
						"open": true,
						"comment": "",
						"data": "",
						"key": "description",
						"type": "object",
						"meta": {},
						"children": [
							{
								"open": false,
								"comment": "",
								"data": "minecraft:iron_golem",
								"key": "identifier",
								"type": "string",
								"meta": {},
								"children": []
							},
							{
								"open": false,
								"comment": "",
								"data": "false",
								"key": "is_spawnable",
								"type": "boolean",
								"meta": {},
								"children": []
							},
							{
								"open": false,
								"comment": "",
								"data": "true",
								"key": "is_summonable",
								"type": "boolean",
								"meta": {},
								"children": []
							},
							{
								"open": false,
								"comment": "",
								"data": "false",
								"key": "is_experimental",
								"type": "boolean",
								"meta": {},
								"children": []
							},
							{
								"open": false,
								"comment": "",
								"data": "",
								"key": "tags",
								"type": "array",
								"meta": {},
								"children": [
									{
										"open": false,
										"comment": "",
										"data": "hit",
										"key": "0",
										"type": "string",
										"meta": {},
										"children": []
									}
								]
							}
						]
					},
					{
						"open": false,
						"comment": "",
						"data": "",
						"key": "component_groups",
						"type": "object",
						"meta": {},
						"children": [
							{
								"open": false,
								"comment": "",
								"data": "",
								"key": "minecraft:player_created",
								"type": "object",
								"meta": {},
								"children": [
									{
										"open": false,
										"comment": "",
										"data": "",
										"key": "minecraft:behavior.hurt_by_target",
										"type": "object",
										"meta": {},
										"children": [
											{
												"open": false,
												"comment": "",
												"data": "2",
												"key": "priority",
												"type": "number",
												"meta": {},
												"children": []
											},
											{
												"open": false,
												"comment": "",
												"data": "",
												"key": "entity_types",
												"type": "object",
												"meta": {},
												"children": [
													{
														"open": false,
														"comment": "",
														"data": "",
														"key": "filters",
														"type": "object",
														"meta": {},
														"children": [
															{
																"open": false,
																"comment": "",
																"data": "",
																"key": "all_of",
																"type": "array",
																"meta": {},
																"children": [
																	{
																		"open": false,
																		"comment": "",
																		"data": "",
																		"key": "0",
																		"type": "object",
																		"meta": {},
																		"children": [
																			{
																				"open": false,
																				"comment": "",
																				"data": "is_family",
																				"key": "test",
																				"type": "string",
																				"meta": {},
																				"children": []
																			},
																			{
																				"open": false,
																				"comment": "",
																				"data": "other",
																				"key": "subject",
																				"type": "string",
																				"meta": {},
																				"children": []
																			},
																			{
																				"open": false,
																				"comment": "",
																				"data": "!=",
																				"key": "operator",
																				"type": "string",
																				"meta": {},
																				"children": []
																			},
																			{
																				"open": false,
																				"comment": "",
																				"data": "player",
																				"key": "value",
																				"type": "string",
																				"meta": {},
																				"children": []
																			}
																		]
																	},
																	{
																		"open": false,
																		"comment": "",
																		"data": "",
																		"key": "1",
																		"type": "object",
																		"meta": {},
																		"children": [
																			{
																				"open": false,
																				"comment": "",
																				"data": "is_family",
																				"key": "test",
																				"type": "string",
																				"meta": {},
																				"children": []
																			},
																			{
																				"open": false,
																				"comment": "",
																				"data": "other",
																				"key": "subject",
																				"type": "string",
																				"meta": {},
																				"children": []
																			},
																			{
																				"open": false,
																				"comment": "",
																				"data": "!=",
																				"key": "operator",
																				"type": "string",
																				"meta": {},
																				"children": []
																			},
																			{
																				"open": false,
																				"comment": "",
																				"data": "creeper",
																				"key": "value",
																				"type": "string",
																				"meta": {},
																				"children": []
																			}
																		]
																	}
																]
															}
														]
													}
												]
											}
										]
									}
								]
							},
							{
								"open": false,
								"comment": "",
								"data": "",
								"key": "minecraft:village_created",
								"type": "object",
								"meta": {},
								"children": [
									{
										"open": false,
										"comment": "",
										"data": "",
										"key": "minecraft:behavior.defend_village_target",
										"type": "object",
										"meta": {},
										"children": [
											{
												"open": false,
												"comment": "",
												"data": "1",
												"key": "priority",
												"type": "number",
												"meta": {},
												"children": []
											}
										]
									},
									{
										"open": false,
										"comment": "",
										"data": "",
										"key": "minecraft:dweller",
										"type": "object",
										"meta": {},
										"children": [
											{
												"open": false,
												"comment": "",
												"data": "village",
												"key": "dwelling_type",
												"type": "string",
												"meta": {},
												"children": []
											},
											{
												"open": false,
												"comment": "",
												"data": "defender",
												"key": "dweller_role",
												"type": "string",
												"meta": {},
												"children": []
											},
											{
												"open": false,
												"comment": "",
												"data": "60",
												"key": "update_interval_base",
												"type": "number",
												"meta": {},
												"children": []
											},
											{
												"open": false,
												"comment": "",
												"data": "40",
												"key": "update_interval_variant",
												"type": "number",
												"meta": {},
												"children": []
											},
											{
												"open": false,
												"comment": "",
												"data": "false",
												"key": "can_find_poi",
												"type": "boolean",
												"meta": {},
												"children": []
											},
											{
												"open": false,
												"comment": "",
												"data": "true",
												"key": "can_migrate",
												"type": "boolean",
												"meta": {},
												"children": []
											},
											{
												"open": false,
												"comment": "",
												"data": "0",
												"key": "first_founding_reward",
												"type": "number",
												"meta": {},
												"children": []
											}
										]
									}
								]
							}
						]
					},
					{
						"open": false,
						"comment": "",
						"data": "",
						"key": "components",
						"type": "object",
						"meta": {},
						"children": [
							{
								"open": false,
								"comment": "",
								"data": "",
								"key": "minecraft:type_family",
								"type": "object",
								"meta": {},
								"children": [
									{
										"open": false,
										"comment": "",
										"data": "",
										"key": "family",
										"type": "array",
										"meta": {},
										"children": [
											{
												"open": false,
												"comment": "",
												"data": "irongolem",
												"key": "0",
												"type": "string",
												"meta": {},
												"children": []
											},
											{
												"open": false,
												"comment": "",
												"data": "mob",
												"key": "1",
												"type": "string",
												"meta": {},
												"children": []
											}
										]
									}
								]
							},
							{
								"open": false,
								"comment": "",
								"data": "",
								"key": "minecraft:nameable",
								"type": "object",
								"meta": {},
								"children": []
							},
							{
								"open": false,
								"comment": "",
								"data": "",
								"key": "minecraft:collision_box",
								"type": "object",
								"meta": {},
								"children": [
									{
										"open": false,
										"comment": "",
										"data": "1.4",
										"key": "width",
										"type": "number",
										"meta": {},
										"children": []
									},
									{
										"open": false,
										"comment": "",
										"data": "2.9",
										"key": "height",
										"type": "number",
										"meta": {},
										"children": []
									}
								]
							},
							{
								"open": false,
								"comment": "",
								"data": "",
								"key": "minecraft:loot",
								"type": "object",
								"meta": {},
								"children": [
									{
										"open": false,
										"comment": "",
										"data": "loot_tables/entities/iron_golem.json",
										"key": "table",
										"type": "string",
										"meta": {},
										"children": []
									}
								]
							},
							{
								"open": false,
								"comment": "",
								"data": "",
								"key": "minecraft:health",
								"type": "object",
								"meta": {},
								"children": [
									{
										"open": false,
										"comment": "",
										"data": "100",
										"key": "value",
										"type": "number",
										"meta": {},
										"children": []
									},
									{
										"open": false,
										"comment": "",
										"data": "100",
										"key": "max",
										"type": "number",
										"meta": {},
										"children": []
									}
								]
							},
							{
								"open": false,
								"comment": "",
								"data": "",
								"key": "minecraft:hurt_on_condition",
								"type": "object",
								"meta": {},
								"children": [
									{
										"open": false,
										"comment": "",
										"data": "",
										"key": "damage_conditions",
										"type": "array",
										"meta": {},
										"children": [
											{
												"open": false,
												"comment": "",
												"data": "",
												"key": "0",
												"type": "object",
												"meta": {},
												"children": [
													{
														"open": false,
														"comment": "",
														"data": "",
														"key": "filters",
														"type": "object",
														"meta": {},
														"children": [
															{
																"open": false,
																"comment": "",
																"data": "in_lava",
																"key": "test",
																"type": "string",
																"meta": {},
																"children": []
															},
															{
																"open": false,
																"comment": "",
																"data": "self",
																"key": "subject",
																"type": "string",
																"meta": {},
																"children": []
															},
															{
																"open": false,
																"comment": "",
																"data": "==",
																"key": "operator",
																"type": "string",
																"meta": {},
																"children": []
															},
															{
																"open": false,
																"comment": "",
																"data": "true",
																"key": "value",
																"type": "boolean",
																"meta": {},
																"children": []
															}
														]
													},
													{
														"open": false,
														"comment": "",
														"data": "lava",
														"key": "cause",
														"type": "string",
														"meta": {},
														"children": []
													},
													{
														"open": false,
														"comment": "",
														"data": "4",
														"key": "damage_per_tick",
														"type": "number",
														"meta": {},
														"children": []
													}
												]
											}
										]
									}
								]
							},
							{
								"open": false,
								"comment": "",
								"data": "",
								"key": "minecraft:movement",
								"type": "object",
								"meta": {},
								"children": [
									{
										"open": false,
										"comment": "",
										"data": "0.25",
										"key": "value",
										"type": "number",
										"meta": {},
										"children": []
									}
								]
							},
							{
								"open": false,
								"comment": "",
								"data": "",
								"key": "minecraft:navigation.walk",
								"type": "object",
								"meta": {},
								"children": [
									{
										"open": false,
										"comment": "",
										"data": "false",
										"key": "can_path_over_water",
										"type": "boolean",
										"meta": {},
										"children": []
									},
									{
										"open": false,
										"comment": "",
										"data": "true",
										"key": "avoid_water",
										"type": "boolean",
										"meta": {},
										"children": []
									},
									{
										"open": false,
										"comment": "",
										"data": "true",
										"key": "avoid_damage_blocks",
										"type": "boolean",
										"meta": {},
										"children": []
									}
								]
							},
							{
								"open": false,
								"comment": "",
								"data": "",
								"key": "minecraft:movement.basic",
								"type": "object",
								"meta": {},
								"children": []
							},
							{
								"open": false,
								"comment": "",
								"data": "",
								"key": "minecraft:jump.static",
								"type": "object",
								"meta": {},
								"children": []
							},
							{
								"open": false,
								"comment": "",
								"data": "",
								"key": "minecraft:can_climb",
								"type": "object",
								"meta": {},
								"children": []
							},
							{
								"open": false,
								"comment": "",
								"data": "",
								"key": "minecraft:attack",
								"type": "object",
								"meta": {},
								"children": [
									{
										"open": false,
										"comment": "",
										"data": "",
										"key": "damage",
										"type": "object",
										"meta": {},
										"children": [
											{
												"open": false,
												"comment": "",
												"data": "7",
												"key": "range_min",
												"type": "number",
												"meta": {},
												"children": []
											},
											{
												"open": false,
												"comment": "",
												"data": "21",
												"key": "range_max",
												"type": "number",
												"meta": {},
												"children": []
											}
										]
									}
								]
							},
							{
								"open": false,
								"comment": "",
								"data": "",
								"key": "minecraft:damage_sensor",
								"type": "object",
								"meta": {},
								"children": [
									{
										"open": false,
										"comment": "",
										"data": "",
										"key": "triggers",
										"type": "object",
										"meta": {},
										"children": [
											{
												"open": false,
												"comment": "",
												"data": "fall",
												"key": "cause",
												"type": "string",
												"meta": {},
												"children": []
											},
											{
												"open": false,
												"comment": "",
												"data": "false",
												"key": "deals_damage",
												"type": "boolean",
												"meta": {},
												"children": []
											}
										]
									}
								]
							},
							{
								"open": false,
								"comment": "",
								"data": "",
								"key": "minecraft:knockback_resistance",
								"type": "object",
								"meta": {},
								"children": [
									{
										"open": false,
										"comment": "",
										"data": "1",
										"key": "value",
										"type": "number",
										"meta": {},
										"children": []
									}
								]
							},
							{
								"open": false,
								"comment": "",
								"data": "",
								"key": "minecraft:leashable",
								"type": "object",
								"meta": {},
								"children": [
									{
										"open": false,
										"comment": "",
										"data": "4",
										"key": "soft_distance",
										"type": "number",
										"meta": {},
										"children": []
									},
									{
										"open": false,
										"comment": "",
										"data": "6",
										"key": "hard_distance",
										"type": "number",
										"meta": {},
										"children": []
									},
									{
										"open": false,
										"comment": "",
										"data": "10",
										"key": "max_distance",
										"type": "number",
										"meta": {},
										"children": []
									}
								]
							},
							{
								"open": false,
								"comment": "",
								"data": "",
								"key": "minecraft:balloonable",
								"type": "object",
								"meta": {},
								"children": []
							},
							{
								"open": false,
								"comment": "",
								"data": "",
								"key": "minecraft:preferred_path",
								"type": "object",
								"meta": {},
								"children": [
									{
										"open": false,
										"comment": "",
										"data": "1",
										"key": "max_fall_blocks",
										"type": "number",
										"meta": {},
										"children": []
									},
									{
										"open": false,
										"comment": "",
										"data": "5",
										"key": "jump_cost",
										"type": "number",
										"meta": {},
										"children": []
									},
									{
										"open": false,
										"comment": "",
										"data": "1.5",
										"key": "default_block_cost",
										"type": "number",
										"meta": {},
										"children": []
									},
									{
										"open": false,
										"comment": "",
										"data": "",
										"key": "preferred_path_blocks",
										"type": "array",
										"meta": {},
										"children": [
											{
												"open": false,
												"comment": "",
												"data": "",
												"key": "0",
												"type": "object",
												"meta": {},
												"children": [
													{
														"open": false,
														"comment": "",
														"data": "0",
														"key": "cost",
														"type": "number",
														"meta": {},
														"children": []
													},
													{
														"open": false,
														"comment": "",
														"data": "",
														"key": "blocks",
														"type": "array",
														"meta": {},
														"children": [
															{
																"open": false,
																"comment": "",
																"data": "grass_path",
																"key": "0",
																"type": "string",
																"meta": {},
																"children": []
															}
														]
													}
												]
											},
											{
												"open": false,
												"comment": "",
												"data": "",
												"key": "1",
												"type": "object",
												"meta": {},
												"children": [
													{
														"open": false,
														"comment": "",
														"data": "1",
														"key": "cost",
														"type": "number",
														"meta": {},
														"children": []
													},
													{
														"open": false,
														"comment": "",
														"data": "",
														"key": "blocks",
														"type": "array",
														"meta": {},
														"children": [
															{
																"open": false,
																"comment": "",
																"data": "cobblestone",
																"key": "0",
																"type": "string",
																"meta": {},
																"children": []
															},
															{
																"open": false,
																"comment": "",
																"data": "stone",
																"key": "1",
																"type": "string",
																"meta": {},
																"children": []
															},
															{
																"open": false,
																"comment": "",
																"data": "stonebrick",
																"key": "2",
																"type": "string",
																"meta": {},
																"children": []
															},
															{
																"open": false,
																"comment": "",
																"data": "sandstone",
																"key": "3",
																"type": "string",
																"meta": {},
																"children": []
															},
															{
																"open": false,
																"comment": "",
																"data": "mossy_cobblestone",
																"key": "4",
																"type": "string",
																"meta": {},
																"children": []
															},
															{
																"open": false,
																"comment": "",
																"data": "stone_slab",
																"key": "5",
																"type": "string",
																"meta": {},
																"children": []
															},
															{
																"open": false,
																"comment": "",
																"data": "stone_slab2",
																"key": "6",
																"type": "string",
																"meta": {},
																"children": []
															},
															{
																"open": false,
																"comment": "",
																"data": "stone_slab3",
																"key": "7",
																"type": "string",
																"meta": {},
																"children": []
															},
															{
																"open": false,
																"comment": "",
																"data": "stone_slab4",
																"key": "8",
																"type": "string",
																"meta": {},
																"children": []
															},
															{
																"open": false,
																"comment": "",
																"data": "double_stone_slab",
																"key": "9",
																"type": "string",
																"meta": {},
																"children": []
															},
															{
																"open": false,
																"comment": "",
																"data": "double_stone_slab2",
																"key": "10",
																"type": "string",
																"meta": {},
																"children": []
															},
															{
																"open": false,
																"comment": "",
																"data": "double_stone_slab3",
																"key": "11",
																"type": "string",
																"meta": {},
																"children": []
															},
															{
																"open": false,
																"comment": "",
																"data": "double_stone_slab4",
																"key": "12",
																"type": "string",
																"meta": {},
																"children": []
															},
															{
																"open": false,
																"comment": "",
																"data": "wooden_slab",
																"key": "13",
																"type": "string",
																"meta": {},
																"children": []
															},
															{
																"open": false,
																"comment": "",
																"data": "double_wooden_slab",
																"key": "14",
																"type": "string",
																"meta": {},
																"children": []
															},
															{
																"open": false,
																"comment": "",
																"data": "planks",
																"key": "15",
																"type": "string",
																"meta": {},
																"children": []
															},
															{
																"open": false,
																"comment": "",
																"data": "brick_block",
																"key": "16",
																"type": "string",
																"meta": {},
																"children": []
															},
															{
																"open": false,
																"comment": "",
																"data": "nether_brick",
																"key": "17",
																"type": "string",
																"meta": {},
																"children": []
															},
															{
																"open": false,
																"comment": "",
																"data": "red_nether_brick",
																"key": "18",
																"type": "string",
																"meta": {},
																"children": []
															},
															{
																"open": false,
																"comment": "",
																"data": "end_bricks",
																"key": "19",
																"type": "string",
																"meta": {},
																"children": []
															},
															{
																"open": false,
																"comment": "",
																"data": "red_sandstone",
																"key": "20",
																"type": "string",
																"meta": {},
																"children": []
															},
															{
																"open": false,
																"comment": "",
																"data": "stained_glass",
																"key": "21",
																"type": "string",
																"meta": {},
																"children": []
															},
															{
																"open": false,
																"comment": "",
																"data": "glass",
																"key": "22",
																"type": "string",
																"meta": {},
																"children": []
															},
															{
																"open": false,
																"comment": "",
																"data": "glowstone",
																"key": "23",
																"type": "string",
																"meta": {},
																"children": []
															},
															{
																"open": false,
																"comment": "",
																"data": "prismarine",
																"key": "24",
																"type": "string",
																"meta": {},
																"children": []
															},
															{
																"open": false,
																"comment": "",
																"data": "emerald_block",
																"key": "25",
																"type": "string",
																"meta": {},
																"children": []
															},
															{
																"open": false,
																"comment": "",
																"data": "diamond_block",
																"key": "26",
																"type": "string",
																"meta": {},
																"children": []
															},
															{
																"open": false,
																"comment": "",
																"data": "lapis_block",
																"key": "27",
																"type": "string",
																"meta": {},
																"children": []
															},
															{
																"open": false,
																"comment": "",
																"data": "gold_block",
																"key": "28",
																"type": "string",
																"meta": {},
																"children": []
															},
															{
																"open": false,
																"comment": "",
																"data": "redstone_block",
																"key": "29",
																"type": "string",
																"meta": {},
																"children": []
															},
															{
																"open": false,
																"comment": "",
																"data": "purple_glazed_terracotta",
																"key": "30",
																"type": "string",
																"meta": {},
																"children": []
															},
															{
																"open": false,
																"comment": "",
																"data": "white_glazed_terracotta",
																"key": "31",
																"type": "string",
																"meta": {},
																"children": []
															},
															{
																"open": false,
																"comment": "",
																"data": "orange_glazed_terracotta",
																"key": "32",
																"type": "string",
																"meta": {},
																"children": []
															},
															{
																"open": false,
																"comment": "",
																"data": "magenta_glazed_terracotta",
																"key": "33",
																"type": "string",
																"meta": {},
																"children": []
															},
															{
																"open": false,
																"comment": "",
																"data": "light_blue_glazed_terracotta",
																"key": "34",
																"type": "string",
																"meta": {},
																"children": []
															},
															{
																"open": false,
																"comment": "",
																"data": "yellow_glazed_terracotta",
																"key": "35",
																"type": "string",
																"meta": {},
																"children": []
															},
															{
																"open": false,
																"comment": "",
																"data": "lime_glazed_terracotta",
																"key": "36",
																"type": "string",
																"meta": {},
																"children": []
															},
															{
																"open": false,
																"comment": "",
																"data": "pink_glazed_terracotta",
																"key": "37",
																"type": "string",
																"meta": {},
																"children": []
															},
															{
																"open": false,
																"comment": "",
																"data": "gray_glazed_terracotta",
																"key": "38",
																"type": "string",
																"meta": {},
																"children": []
															},
															{
																"open": false,
																"comment": "",
																"data": "silver_glazed_terracotta",
																"key": "39",
																"type": "string",
																"meta": {},
																"children": []
															},
															{
																"open": false,
																"comment": "",
																"data": "cyan_glazed_terracotta",
																"key": "40",
																"type": "string",
																"meta": {},
																"children": []
															},
															{
																"open": false,
																"comment": "",
																"data": "blue_glazed_terracotta",
																"key": "41",
																"type": "string",
																"meta": {},
																"children": []
															},
															{
																"open": false,
																"comment": "",
																"data": "brown_glazed_terracotta",
																"key": "42",
																"type": "string",
																"meta": {},
																"children": []
															},
															{
																"open": false,
																"comment": "",
																"data": "green_glazed_terracotta",
																"key": "43",
																"type": "string",
																"meta": {},
																"children": []
															},
															{
																"open": false,
																"comment": "",
																"data": "red_glazed_terracotta",
																"key": "44",
																"type": "string",
																"meta": {},
																"children": []
															},
															{
																"open": false,
																"comment": "",
																"data": "black_glazed_terracotta",
																"key": "45",
																"type": "string",
																"meta": {},
																"children": []
															}
														]
													}
												]
											},
											{
												"open": false,
												"comment": "",
												"data": "",
												"key": "2",
												"type": "object",
												"meta": {},
												"children": [
													{
														"open": false,
														"comment": "",
														"data": "50",
														"key": "cost",
														"type": "number",
														"meta": {},
														"children": []
													},
													{
														"open": false,
														"comment": "",
														"data": "",
														"key": "blocks",
														"type": "array",
														"meta": {},
														"children": [
															{
																"open": false,
																"comment": "",
																"data": "bed",
																"key": "0",
																"type": "string",
																"meta": {},
																"children": []
															},
															{
																"open": false,
																"comment": "",
																"data": "lectern",
																"key": "1",
																"type": "string",
																"meta": {},
																"children": []
															},
															{
																"open": false,
																"comment": "",
																"data": "composter",
																"key": "2",
																"type": "string",
																"meta": {},
																"children": []
															},
															{
																"open": false,
																"comment": "",
																"data": "grindstone",
																"key": "3",
																"type": "string",
																"meta": {},
																"children": []
															},
															{
																"open": false,
																"comment": "",
																"data": "blast_furnace",
																"key": "4",
																"type": "string",
																"meta": {},
																"children": []
															},
															{
																"open": false,
																"comment": "",
																"data": "smoker",
																"key": "5",
																"type": "string",
																"meta": {},
																"children": []
															},
															{
																"open": false,
																"comment": "",
																"data": "fletching_table",
																"key": "6",
																"type": "string",
																"meta": {},
																"children": []
															},
															{
																"open": false,
																"comment": "",
																"data": "cartography_table",
																"key": "7",
																"type": "string",
																"meta": {},
																"children": []
															},
															{
																"open": false,
																"comment": "",
																"data": "brewing_stand",
																"key": "8",
																"type": "string",
																"meta": {},
																"children": []
															},
															{
																"open": false,
																"comment": "",
																"data": "smithing_table",
																"key": "9",
																"type": "string",
																"meta": {},
																"children": []
															},
															{
																"open": false,
																"comment": "",
																"data": "cauldron",
																"key": "10",
																"type": "string",
																"meta": {},
																"children": []
															},
															{
																"open": false,
																"comment": "",
																"data": "barrel",
																"key": "11",
																"type": "string",
																"meta": {},
																"children": []
															},
															{
																"open": false,
																"comment": "",
																"data": "loom",
																"key": "12",
																"type": "string",
																"meta": {},
																"children": []
															},
															{
																"open": false,
																"comment": "",
																"data": "stonecutter",
																"key": "13",
																"type": "string",
																"meta": {},
																"children": []
															}
														]
													}
												]
											}
										]
									}
								]
							},
							{
								"open": false,
								"comment": "",
								"data": "",
								"key": "minecraft:behavior.target_when_pushed",
								"type": "object",
								"meta": {},
								"children": [
									{
										"open": false,
										"comment": "",
										"data": "1",
										"key": "priority",
										"type": "number",
										"meta": {},
										"children": []
									},
									{
										"open": false,
										"comment": "",
										"data": "5",
										"key": "percent_chance",
										"type": "number",
										"meta": {},
										"children": []
									},
									{
										"open": false,
										"comment": "",
										"data": "",
										"key": "entity_types",
										"type": "array",
										"meta": {},
										"children": [
											{
												"open": false,
												"comment": "",
												"data": "",
												"key": "0",
												"type": "object",
												"meta": {},
												"children": [
													{
														"open": false,
														"comment": "",
														"data": "",
														"key": "filters",
														"type": "object",
														"meta": {},
														"children": [
															{
																"open": false,
																"comment": "",
																"data": "",
																"key": "all_of",
																"type": "array",
																"meta": {},
																"children": [
																	{
																		"open": false,
																		"comment": "",
																		"data": "",
																		"key": "0",
																		"type": "object",
																		"meta": {},
																		"children": [
																			{
																				"open": false,
																				"comment": "",
																				"data": "is_family",
																				"key": "test",
																				"type": "string",
																				"meta": {},
																				"children": []
																			},
																			{
																				"open": false,
																				"comment": "",
																				"data": "other",
																				"key": "subject",
																				"type": "string",
																				"meta": {},
																				"children": []
																			},
																			{
																				"open": false,
																				"comment": "",
																				"data": "monster",
																				"key": "value",
																				"type": "string",
																				"meta": {},
																				"children": []
																			}
																		]
																	},
																	{
																		"open": false,
																		"comment": "",
																		"data": "",
																		"key": "1",
																		"type": "object",
																		"meta": {},
																		"children": [
																			{
																				"open": false,
																				"comment": "",
																				"data": "is_family",
																				"key": "test",
																				"type": "string",
																				"meta": {},
																				"children": []
																			},
																			{
																				"open": false,
																				"comment": "",
																				"data": "other",
																				"key": "subject",
																				"type": "string",
																				"meta": {},
																				"children": []
																			},
																			{
																				"open": false,
																				"comment": "",
																				"data": "!=",
																				"key": "operator",
																				"type": "string",
																				"meta": {},
																				"children": []
																			},
																			{
																				"open": false,
																				"comment": "",
																				"data": "creeper",
																				"key": "value",
																				"type": "string",
																				"meta": {},
																				"children": []
																			}
																		]
																	}
																]
															}
														]
													}
												]
											}
										]
									}
								]
							},
							{
								"open": false,
								"comment": "",
								"data": "",
								"key": "minecraft:behavior.melee_attack",
								"type": "object",
								"meta": {},
								"children": [
									{
										"open": false,
										"comment": "",
										"data": "1",
										"key": "priority",
										"type": "number",
										"meta": {},
										"children": []
									},
									{
										"open": false,
										"comment": "",
										"data": "1",
										"key": "target_dist",
										"type": "number",
										"meta": {},
										"children": []
									},
									{
										"open": false,
										"comment": "",
										"data": "true",
										"key": "track_target",
										"type": "boolean",
										"meta": {},
										"children": []
									}
								]
							},
							{
								"open": false,
								"comment": "",
								"data": "",
								"key": "minecraft:behavior.move_towards_target",
								"type": "object",
								"meta": {},
								"children": [
									{
										"open": false,
										"comment": "",
										"data": "2",
										"key": "priority",
										"type": "number",
										"meta": {},
										"children": []
									},
									{
										"open": false,
										"comment": "",
										"data": "0.9",
										"key": "speed_multiplier",
										"type": "number",
										"meta": {},
										"children": []
									},
									{
										"open": false,
										"comment": "",
										"data": "32",
										"key": "within_radius",
										"type": "number",
										"meta": {},
										"children": []
									}
								]
							},
							{
								"open": false,
								"comment": "",
								"data": "",
								"key": "minecraft:behavior.move_through_village",
								"type": "object",
								"meta": {},
								"children": [
									{
										"open": false,
										"comment": "",
										"data": "3",
										"key": "priority",
										"type": "number",
										"meta": {},
										"children": []
									},
									{
										"open": false,
										"comment": "",
										"data": "0.6",
										"key": "speed_multiplier",
										"type": "number",
										"meta": {},
										"children": []
									},
									{
										"open": false,
										"comment": "",
										"data": "true",
										"key": "only_at_night",
										"type": "boolean",
										"meta": {},
										"children": []
									}
								]
							},
							{
								"open": false,
								"comment": "",
								"data": "",
								"key": "minecraft:behavior.move_towards_restriction",
								"type": "object",
								"meta": {},
								"children": [
									{
										"open": false,
										"comment": "",
										"data": "4",
										"key": "priority",
										"type": "number",
										"meta": {},
										"children": []
									},
									{
										"open": false,
										"comment": "",
										"data": "1",
										"key": "speed_multiplier",
										"type": "number",
										"meta": {},
										"children": []
									}
								]
							},
							{
								"open": false,
								"comment": "",
								"data": "",
								"key": "minecraft:behavior.offer_flower",
								"type": "object",
								"meta": {},
								"children": [
									{
										"open": false,
										"comment": "",
										"data": "5",
										"key": "priority",
										"type": "number",
										"meta": {},
										"children": []
									}
								]
							},
							{
								"open": false,
								"comment": "",
								"data": "",
								"key": "minecraft:behavior.random_stroll",
								"type": "object",
								"meta": {},
								"children": [
									{
										"open": false,
										"comment": "",
										"data": "6",
										"key": "priority",
										"type": "number",
										"meta": {},
										"children": []
									},
									{
										"open": false,
										"comment": "",
										"data": "1",
										"key": "speed_multiplier",
										"type": "number",
										"meta": {},
										"children": []
									},
									{
										"open": false,
										"comment": "",
										"data": "16",
										"key": "xz_dist",
										"type": "number",
										"meta": {},
										"children": []
									}
								]
							},
							{
								"open": false,
								"comment": "",
								"data": "",
								"key": "minecraft:behavior.look_at_player",
								"type": "object",
								"meta": {},
								"children": [
									{
										"open": false,
										"comment": "",
										"data": "7",
										"key": "priority",
										"type": "number",
										"meta": {},
										"children": []
									},
									{
										"open": false,
										"comment": "",
										"data": "6",
										"key": "look_distance",
										"type": "number",
										"meta": {},
										"children": []
									},
									{
										"open": false,
										"comment": "",
										"data": "0.02",
										"key": "probability",
										"type": "number",
										"meta": {},
										"children": []
									}
								]
							},
							{
								"open": false,
								"comment": "",
								"data": "",
								"key": "minecraft:behavior.random_look_around",
								"type": "object",
								"meta": {},
								"children": [
									{
										"open": false,
										"comment": "",
										"data": "8",
										"key": "priority",
										"type": "number",
										"meta": {},
										"children": []
									}
								]
							},
							{
								"open": false,
								"comment": "",
								"data": "",
								"key": "minecraft:behavior.nearest_attackable_target",
								"type": "object",
								"meta": {},
								"children": [
									{
										"open": false,
										"comment": "",
										"data": "3",
										"key": "priority",
										"type": "number",
										"meta": {},
										"children": []
									},
									{
										"open": false,
										"comment": "",
										"data": "",
										"key": "entity_types",
										"type": "array",
										"meta": {},
										"children": [
											{
												"open": false,
												"comment": "",
												"data": "",
												"key": "0",
												"type": "object",
												"meta": {},
												"children": [
													{
														"open": false,
														"comment": "",
														"data": "",
														"key": "filters",
														"type": "object",
														"meta": {},
														"children": [
															{
																"open": false,
																"comment": "",
																"data": "",
																"key": "all_of",
																"type": "array",
																"meta": {},
																"children": [
																	{
																		"open": false,
																		"comment": "",
																		"data": "",
																		"key": "0",
																		"type": "object",
																		"meta": {},
																		"children": [
																			{
																				"open": false,
																				"comment": "",
																				"data": "is_family",
																				"key": "test",
																				"type": "string",
																				"meta": {},
																				"children": []
																			},
																			{
																				"open": false,
																				"comment": "",
																				"data": "other",
																				"key": "subject",
																				"type": "string",
																				"meta": {},
																				"children": []
																			},
																			{
																				"open": false,
																				"comment": "",
																				"data": "monster",
																				"key": "value",
																				"type": "string",
																				"meta": {},
																				"children": []
																			}
																		]
																	},
																	{
																		"open": false,
																		"comment": "",
																		"data": "",
																		"key": "1",
																		"type": "object",
																		"meta": {},
																		"children": [
																			{
																				"open": false,
																				"comment": "",
																				"data": "is_family",
																				"key": "test",
																				"type": "string",
																				"meta": {},
																				"children": []
																			},
																			{
																				"open": false,
																				"comment": "",
																				"data": "other",
																				"key": "subject",
																				"type": "string",
																				"meta": {},
																				"children": []
																			},
																			{
																				"open": false,
																				"comment": "",
																				"data": "!=",
																				"key": "operator",
																				"type": "string",
																				"meta": {},
																				"children": []
																			},
																			{
																				"open": false,
																				"comment": "",
																				"data": "creeper",
																				"key": "value",
																				"type": "string",
																				"meta": {},
																				"children": []
																			}
																		]
																	}
																]
															}
														]
													},
													{
														"open": false,
														"comment": "",
														"data": "10",
														"key": "within_default",
														"type": "number",
														"meta": {},
														"children": []
													}
												]
											}
										]
									},
									{
										"open": false,
										"comment": "",
										"data": "true",
										"key": "must_see",
										"type": "boolean",
										"meta": {},
										"children": []
									},
									{
										"open": false,
										"comment": "",
										"data": "true",
										"key": "must_reach",
										"type": "boolean",
										"meta": {},
										"children": []
									}
								]
							},
							{
								"open": false,
								"comment": "",
								"data": "",
								"key": "minecraft:behavior.hurt_by_target",
								"type": "object",
								"meta": {},
								"children": [
									{
										"open": false,
										"comment": "",
										"data": "2",
										"key": "priority",
										"type": "number",
										"meta": {},
										"children": []
									},
									{
										"open": false,
										"comment": "",
										"data": "",
										"key": "entity_types",
										"type": "object",
										"meta": {},
										"children": [
											{
												"open": false,
												"comment": "",
												"data": "",
												"key": "filters",
												"type": "object",
												"meta": {},
												"children": [
													{
														"open": false,
														"comment": "",
														"data": "is_family",
														"key": "test",
														"type": "string",
														"meta": {},
														"children": []
													},
													{
														"open": false,
														"comment": "",
														"data": "other",
														"key": "subject",
														"type": "string",
														"meta": {},
														"children": []
													},
													{
														"open": false,
														"comment": "",
														"data": "!=",
														"key": "operator",
														"type": "string",
														"meta": {},
														"children": []
													},
													{
														"open": false,
														"comment": "",
														"data": "creeper",
														"key": "value",
														"type": "string",
														"meta": {},
														"children": []
													}
												]
											}
										]
									}
								]
							},
							{
								"open": false,
								"comment": "",
								"data": "",
								"key": "minecraft:persistent",
								"type": "object",
								"meta": {},
								"children": []
							},
							{
								"open": false,
								"comment": "",
								"data": "",
								"key": "minecraft:physics",
								"type": "object",
								"meta": {},
								"children": []
							},
							{
								"open": false,
								"comment": "",
								"data": "",
								"key": "minecraft:pushable",
								"type": "object",
								"meta": {},
								"children": [
									{
										"open": false,
										"comment": "",
										"data": "true",
										"key": "is_pushable",
										"type": "boolean",
										"meta": {},
										"children": []
									},
									{
										"open": false,
										"comment": "",
										"data": "true",
										"key": "is_pushable_by_piston",
										"type": "boolean",
										"meta": {},
										"children": []
									}
								]
							},
							{
								"open": false,
								"comment": "",
								"data": "",
								"key": "minecraft:follow_range",
								"type": "object",
								"meta": {},
								"children": [
									{
										"open": false,
										"comment": "",
										"data": "64",
										"key": "value",
										"type": "number",
										"meta": {},
										"children": []
									}
								]
							}
						]
					},
					{
						"open": false,
						"comment": "",
						"data": "",
						"key": "events",
						"type": "object",
						"meta": {},
						"children": [
							{
								"open": false,
								"comment": "",
								"data": "",
								"key": "minecraft:from_player",
								"type": "object",
								"meta": {},
								"children": [
									{
										"open": false,
										"comment": "",
										"data": "",
										"key": "add",
										"type": "object",
										"meta": {},
										"children": [
											{
												"open": false,
												"comment": "",
												"data": "",
												"key": "component_groups",
												"type": "array",
												"meta": {},
												"children": [
													{
														"open": false,
														"comment": "",
														"data": "minecraft:player_created",
														"key": "0",
														"type": "string",
														"meta": {},
														"children": []
													}
												]
											}
										]
									}
								]
							},
							{
								"open": false,
								"comment": "",
								"data": "",
								"key": "minecraft:from_village",
								"type": "object",
								"meta": {},
								"children": [
									{
										"open": false,
										"comment": "",
										"data": "",
										"key": "add",
										"type": "object",
										"meta": {},
										"children": [
											{
												"open": false,
												"comment": "",
												"data": "",
												"key": "component_groups",
												"type": "array",
												"meta": {},
												"children": [
													{
														"open": false,
														"comment": "",
														"data": "minecraft:village_created",
														"key": "0",
														"type": "string",
														"meta": {},
														"children": []
													}
												]
											}
										]
									}
								]
							}
						]
					}
				]
			}
		]
	}
}